{
    "frontend": [
        {
            "name": "React"
        },
        {
            "name": "TypeScript"
        },
        {
            "name": "JavaScript"
        },
        {
            "name": "Axios"
        },
        {
            "name": "Vite"
        },
        {
            "name": "HTML"
        },
        {
            "name": "CSS"
        },
        {
            "name": "Flutter"
        }
    ],
    "backend": [
        {
            "name": "Node.js"
        },
        {
            "name": "Go (Gin)"
        },
        {
            "name": "REST APIs"
        }
    ],
    "languages": [
        {
            "name": "JavaScript"
        },
        {
            "name": "TypeScript"
        },
        {
            "name": "Dart"
        },
        {
            "name": "C/C++"
        },
        {
            "name": "Java"
        },
        {
            "name": "Python (Basic)"
        },
        {
            "name": "PHP (Basic)"
        }
    ],
    "database": [
        {
            "name": "PostgreSQL"
        },
        {
            "name": "MongoDB"
        },
        {
            "name": "MySQL"
        },
        {
            "name": "SQLite"
        },
        {
            "name": "Redis"
        }
    ],
    "technologies": [
        {
            "name": "JWT Authentication"
        },
        {
            "name": "WebSockets"
        },
        {
            "name": "Stripe"
        },
        {
            "name": "Cloudinary"
        },
        {
            "name": "RabbitMQ"
        },
        {
            "name": "Internationalization (i18n)"
        },
        {
            "name": "Unit Testing (JUnit)"
        }
    ],
    "hardware": [
        {
            "name": "Arduino"
        },
        {
            "name": "Raspberry Pi"
        },
        {
            "name": "Sensors Integration"
        },
        {
            "name": "Motor Control (DC, Servo, Stepper)"
        }
    ],
    "tools": [
        {
            "name": "Git"
        },
        {
            "name": "Docker"
        },
        {
            "name": "Postman"
        },
        {
            "name": "Linux"
        },
        {
            "name": "Netlify"
        },
        {
            "name": "Ngrok"
        },
        {
            "name": "CI/CD"
        },
        {
            "name": "Kubernetes (Basic)"
        },
        {
            "name": "AWS (Basic)"
        }
    ]
}